fedorov/__init__.py
fedorov/fedorov.py
fedorov/crystal_data/Aflow_processed_data.csv
fedorov/crystal_data/Aflow_raw_data.csv
fedorov/crystal_data/plane_group_info.pickle
fedorov/crystal_data/plane_group_lattice_mapping.json
fedorov/crystal_data/point_group_name_mapping.json
fedorov/crystal_data/point_group_quat_dict.json
fedorov/crystal_data/point_group_rotation_matrix_dict.pickle
fedorov/crystal_data/space_group_100_Wyckoff_site_data.json
fedorov/crystal_data/space_group_101_Wyckoff_site_data.json
fedorov/crystal_data/space_group_102_Wyckoff_site_data.json
fedorov/crystal_data/space_group_103_Wyckoff_site_data.json
fedorov/crystal_data/space_group_104_Wyckoff_site_data.json
fedorov/crystal_data/space_group_105_Wyckoff_site_data.json
fedorov/crystal_data/space_group_106_Wyckoff_site_data.json
fedorov/crystal_data/space_group_107_Wyckoff_site_data.json
fedorov/crystal_data/space_group_108_Wyckoff_site_data.json
fedorov/crystal_data/space_group_109_Wyckoff_site_data.json
fedorov/crystal_data/space_group_10_Wyckoff_site_data.json
fedorov/crystal_data/space_group_110_Wyckoff_site_data.json
fedorov/crystal_data/space_group_111_Wyckoff_site_data.json
fedorov/crystal_data/space_group_112_Wyckoff_site_data.json
fedorov/crystal_data/space_group_113_Wyckoff_site_data.json
fedorov/crystal_data/space_group_114_Wyckoff_site_data.json
fedorov/crystal_data/space_group_115_Wyckoff_site_data.json
fedorov/crystal_data/space_group_116_Wyckoff_site_data.json
fedorov/crystal_data/space_group_117_Wyckoff_site_data.json
fedorov/crystal_data/space_group_118_Wyckoff_site_data.json
fedorov/crystal_data/space_group_119_Wyckoff_site_data.json
fedorov/crystal_data/space_group_11_Wyckoff_site_data.json
fedorov/crystal_data/space_group_120_Wyckoff_site_data.json
fedorov/crystal_data/space_group_121_Wyckoff_site_data.json
fedorov/crystal_data/space_group_122_Wyckoff_site_data.json
fedorov/crystal_data/space_group_123_Wyckoff_site_data.json
fedorov-0.1.0.dist-info/METADATA
fedorov-0.1.0.dist-info/WHEEL
fedorov-0.1.0.dist-info/top_level.txt
fedorov-0.1.0.dist-info/RECORD
