Metadata-Version: 2.1
Name: fedorov
Version: 0.1.0
Summary: A python code repo to initialize different crystal structures based on Pearson symbol or space group
Home-page: https://github.com/zhou-pj/crystal_database
Author: Pengji Zhou
Author-email: zhoupj@umich.edu
License: UNKNOWN
Platform: UNKNOWN
Classifier: Programming Language :: Python :: 3
Classifier: License :: OSI Approved :: BSD License
Classifier: Topic :: Scientific/Engineering
Requires-Python: >=3.3
Requires-Dist: numpy (>=1.10)
Requires-Dist: spglib (>=1.9.0)
Requires-Dist: pandas (>=0.20.0)
Requires-Dist: rowan (>=1.0.0)
